{
    "bridge": {
        "name": "Homebridge",
        "username": "CC:22:3D:E3:CE:31",
        "port": 51826,
        "pin": "031-45-155" /* Will be replaced accordingly */
    },
    
    "description": "Garage HomeBridge",

    "accessories": [
        {
            "accessory": "Motion Sensor",
            "name": "Garage Motion Sensor",
            "pirPin": 4
        },
	{
	    "accessory": "GPIOGarageDoor",
	    "name": "Garage Door",
	    "doorSwitchPin": 18,
	    "doorSensorPin": 17,
            "isNCSensor": true,
            "doorOpensInSeconds": 15
	}
    ],

    "platforms": [
    ]
}
